.travis.yml
LICENSE.txt
MANIFEST.in
README.md
README.rst
setup.cfg
setup.py
geohash_hilbert/__init__.py
geohash_hilbert/_hilbert.py
geohash_hilbert/_hilbert_cython.pyx
geohash_hilbert/_int2str.py
geohash_hilbert/_utils.py
geohash_hilbert.egg-info/PKG-INFO
geohash_hilbert.egg-info/SOURCES.txt
geohash_hilbert.egg-info/dependency_links.txt
geohash_hilbert.egg-info/top_level.txt
tests/test_hilbert.py
tests/test_int2str.py
tests/test_utils.py