Metadata-Version: 1.1
Name: geohash-hilbert
Version: 1.2
Summary: Geohash a lng/lat coordinate using the hilbert curve.
Home-page: https://github.com/tammoippen/geohash-hilbert
Author: Tammo Ippen
Author-email: tammo.ippen@posteo.de
License: MIT
Download-URL: https://github.com/tammoippen/geohash-hilbert/archive/v1.2.tar.gz
Keywords: geohash,hilbert,space filling curve,geometry
Platform: UNKNOWN
Classifier: License :: OSI Approved :: MIT License
Classifier: Programming Language :: Python
Classifier: Programming Language :: Python :: 2.7
Classifier: Programming Language :: Python :: 3
Classifier: Programming Language :: Python :: 3.5
Classifier: Programming Language :: Python :: 3.6
Classifier: Programming Language :: Python :: Implementation :: CPython
Classifier: Programming Language :: Python :: Implementation :: PyPy
